{
  "theme_name": "lbmgiftcard Core",
  "selected_preset": 0,
  "field_groups": [
    {
      "name": "Theme Colors"
    }
  ],
  "theme_presets": [
    {
      "isCustom": 0,
      "name": "Default",
      "fields": [
        {
          "label": "Primary Color",
          "name": "primary_color",
          "type": 2,
          "value": "43464e",
          "group": 0
        },
        {
          "label": "Secondary color",
          "name": "secondary_color",
          "type": 2,
          "value": "000",
          "group": 0
        }
      ]
    },
    {
      "isCustom": 1,
      "name": "Custom",
      "fields": [
        {
          "label": "Primary Color",
          "name": "primary_color",
          "type": 2,
          "value": "43464e",
          "group": 0
        },
        {
          "label": "Secondary color",
          "name": "secondary_color",
          "type": 2,
          "value": "000",
          "group": 0
        }
      ]
    }
  ]
}

